{
    "elogic_shops": {
        "column": {
            "shop_id": true,
            "shop_name": true,
            "description": true,
            "img_url": true,
            "shop_city": true,
            "shop_zip": true,
            "shop_state": true,
            "shop_address": true,
            "work_schedule": true,
            "holiday_work_schedule": true,
            "latitude": true,
            "longitude": true,
            "url_key": true
        },
        "constraint": {
            "PRIMARY": true,
            "ELOGIC_SHOPS_SHOP_NAME": true,
            "ELOGIC_SHOPS_URL_KEY": true
        }
    },
    "shop_products": {
        "column": {
            "entity_id": true,
            "shop_id": true,
            "product_id": true
        },
        "constraint": {
            "PRIMARY": true,
            "SHOP_PRODUCTS_SHOP_ID_ELOGIC_SHOPS_SHOP_ID": true,
            "SHOP_PRODUCTS_PRODUCT_ID_CATALOG_PRODUCT_ENTITY_ENTITY_ID": true
        }
    }
}